xtts_api_server/__init__.py
xtts_api_server/__main__.py
xtts_api_server/modeldownloader.py
xtts_api_server/server.py
xtts_api_server/tts_funcs.py
xtts_api_server/RealtimeTTS/README.MD
xtts_api_server/RealtimeTTS/__init__.py
xtts_api_server/RealtimeTTS/coqui_test.py
xtts_api_server/RealtimeTTS/silence.wav
xtts_api_server/RealtimeTTS/stream_player.py
xtts_api_server/RealtimeTTS/text_to_stream.py
xtts_api_server/RealtimeTTS/threadsafe_generators.py
xtts_api_server/RealtimeTTS/engines/__init__.py
xtts_api_server/RealtimeTTS/engines/base_engine.py
xtts_api_server/RealtimeTTS/engines/coqui_default_voice.json
xtts_api_server/RealtimeTTS/engines/coqui_engine.py
xtts_api_server-0.9.0.dist-info/METADATA
xtts_api_server-0.9.0.dist-info/WHEEL
xtts_api_server-0.9.0.dist-info/licenses/LICENSE
xtts_api_server-0.9.0.dist-info/RECORD
