Metadata-Version: 2.1
Name: xtts-api-server
Version: 0.9.0
Summary: A simple FastAPI server to host XTTSv2
Project-URL: Homepage, https://github.com/daswer123/xtts-api-server
Project-URL: Bug Tracker, https://github.com/daswer123/xtts-api-server/issues
Author-email: daswer123 <daswerq123@gmail.com>
License-File: LICENSE
Classifier: License :: OSI Approved :: MIT License
Classifier: Operating System :: OS Independent
Classifier: Programming Language :: Python :: 3
Requires-Python: >=3.9
Requires-Dist: coqui-tts[languages]==0.24.1
Requires-Dist: cutlet
Requires-Dist: fastapi>=0.104.1
Requires-Dist: fugashi[unidic-lite]
Requires-Dist: loguru
Requires-Dist: pyaudio==0.2.14
Requires-Dist: pydantic
Requires-Dist: pydub
Requires-Dist: python-dotenv
Requires-Dist: pyttsx3==2.90
Requires-Dist: requests==2.31.0
Requires-Dist: spacy==3.7.2
Requires-Dist: stream2sentence==0.2.2
Requires-Dist: torch
Requires-Dist: torchaudio
Requires-Dist: transformers==4.36.2
Requires-Dist: uuid
Requires-Dist: uvicorn
